sssdldapauth/__init__.py
sssdldapauth/cli.py
sssdldapauth/deobfuscate.py
sssdldapauth/py.typed
sssdldapauth-0.0.2.dist-info/LICENSE.txt
sssdldapauth-0.0.2.dist-info/METADATA
sssdldapauth-0.0.2.dist-info/WHEEL
sssdldapauth-0.0.2.dist-info/entry_points.txt
sssdldapauth-0.0.2.dist-info/top_level.txt
sssdldapauth-0.0.2.dist-info/RECORD
