Metadata-Version: 2.1
Name: sssdldapauth
Version: 0.0.2
Summary: Supports deobfuscating LDAP passwords contained in (System Security Services Daemon) sssd.conf files.
Home-page: https://github.com/jteppinette/python-sssd-ldap-auth
Author: Joshua Taylor Eppinette
Author-email: jteppinette@jteppinette.com
License: MIT
Platform: UNKNOWN
Requires-Python: >=3.6
License-File: LICENSE.txt
Requires-Dist: click
Requires-Dist: cryptography
